{"name":"Login exitoso","id":"login;login-exitoso","testSteps":[{"number":1,"description":"Given ingreso al sistema con el rol \"Admin\"","duration":277,"startTime":"2024-08-27T21:06:01.258565500-05:00[America/Lima]","result":"SUCCESS","precondition":false,"level":0},{"number":2,"description":"When ingreso las credenciales","duration":6,"startTime":"2024-08-27T21:06:01.548551900-05:00[America/Lima]","result":"SUCCESS","precondition":false,"level":0},{"number":3,"description":"Then se muestra la web principal","duration":7,"startTime":"2024-08-27T21:06:01.556522700-05:00[America/Lima]","result":"SUCCESS","precondition":false,"level":0}],"userStory":{"id":"login","storyName":"Login","displayName":"Login","path":"login.feature","type":"feature"},"featureTag":{"name":"Login","type":"feature","displayName":"Login"},"title":"Login exitoso","description":"","tags":[{"name":"successful","type":"tag","displayName":"successful"},{"name":"Login","type":"feature","displayName":"Login"}],"startTime":"2024-08-27T21:06:00.858268-05:00[America/Lima]","duration":717,"projectKey":"","isManualTestingUpToDate":false,"manual":false,"testSource":"Cucumber","actors":[{"name":"Admin","can":["browse the web"]}],"result":"SUCCESS"}